{
  "findings": [
    {
      "id": 1,
      "severity": "critical",
      "area": "Build/Deployment",
      "page": "All pages (production build)",
      "title": "Production Build Completely Broken - White Screen of Death",
      "description": "The production build (npm run preview) shows a completely blank white screen. CSP policy blocks inline event handlers with strict nonce + strict-dynamic enforcement.",
      "impact": "Application is 100% unusable in production mode. This is a SHIP BLOCKER.",
      "screenshot": "./screenshots/00-landing-initial.png",
      "reproduction": ["Run: npm run build", "Run: npm run preview", "Navigate to http://localhost:4173/", "Observe: Blank white screen, no UI rendered"],
      "consoleErrors": ["Refused to execute inline event handler because it violates CSP directive", "frame-ancestors ignored when delivered via <meta> element", "X-Frame-Options may only be set via HTTP header"],
      "fix": "Remove inline event handlers from HTML. Move CSP to HTTP headers. Fix vite-plugin-csp.ts nonce injection.",
      "file": "vite-plugin-csp.ts"
    },
    {
      "id": 2,
      "severity": "high",
      "area": "Security Headers",
      "page": "All pages",
      "title": "CSP Headers Incorrectly Set via Meta Tags",
      "description": "X-Frame-Options and frame-ancestors set via <meta> instead of HTTP headers. Browsers ignore these.",
      "impact": "Security headers ineffective. Vulnerable to clickjacking.",
      "screenshot": "./screenshots/05-main-dashboard.png",
      "reproduction": ["Open any page", "Check console", "See X-Frame-Options warning"],
      "consoleErrors": ["X-Frame-Options may only be set via an HTTP header"],
      "fix": "Move headers to server config (Nginx/Vercel headers)",
      "file": "index.html or server config"
    },
    {
      "id": 3,
      "severity": "medium",
      "area": "React Components",
      "page": "Dashboard",
      "title": "React Ref Warnings - Function Components",
      "description": "NoteTemplates and Part2Badge components show 'cannot be given refs' warnings",
      "impact": "May break ref forwarding in edge cases",
      "screenshot": "./screenshots/05-main-dashboard.png",
      "reproduction": ["Login", "View console", "See React ref warnings"],
      "consoleErrors": ["Function components cannot be given refs"],
      "fix": "Wrap with React.forwardRef()",
      "file": "src/components/NoteTemplates.tsx:30, Part2Badge.tsx:24"
    },
    {
      "id": 4,
      "severity": "medium",
      "area": "Forms",
      "page": "/auth",
      "title": "Missing Autocomplete Attributes",
      "description": "Password fields lack autocomplete='current-password'",
      "impact": "Browsers won't offer password save/autofill",
      "screenshot": "./screenshots/02-auth-sign-in.png",
      "reproduction": ["Go to /auth", "Check console autocomplete warning"],
      "consoleErrors": ["Input elements should have autocomplete attributes"],
      "fix": "Add autoComplete='email' and autoComplete='current-password'",
      "file": "src/pages/Auth.tsx"
    },
    {
      "id": 5,
      "severity": "medium",
      "area": "React State",
      "page": "Dashboard",
      "title": "Select Component State Management Issue",
      "description": "Client selector switching uncontrolled <-> controlled",
      "impact": "Potential dropdown state bugs",
      "screenshot": "./screenshots/05-main-dashboard.png",
      "reproduction": ["Login", "Check console", "See Select warning"],
      "consoleErrors": ["Select is changing from uncontrolled to controlled"],
      "fix": "Always provide value prop: value={value || ''}",
      "file": "ChatInterface or similar"
    }
  ],
  "summary": {
    "totalIssues": 5,
    "critical": 1,
    "high": 1,
    "medium": 3,
    "shipBlockers": 1
  }
}